<?xml version="1.0"?><eml:eml xmlns:eml="eml://ecoinformatics.org/eml-2.0.1" xmlns:stmml="http://www.xml-cml.org/schema/stmml" xmlns:xsi="http://www.w3.org/2001/XMLSchema-instance" xmlns:ds="eml://ecoinformatics.org/dataset-2.0.1" packageId="knb-lter-vcr.95.8" system="VCR" xsi:schemaLocation="eml://ecoinformatics.org/eml-2.0.1 http://gce-lter.marsci.uga.edu/lter/files/schemas/eml-201/eml.xsd" scope="system"><dataset id="95" system="VCR" scope="document"><alternateIdentifier>VCR00074</alternateIdentifier><title>Water Quality of Virginia Coastal Bays - Total suspended solids and chlorophyll data 1992-2004</title><creator scope="document"><individualName><salutation>Dr.</salutation><givenName>Linda</givenName><surName>Blum</surName></individualName><address scope="document"><deliveryPoint>University of Virginia, Department of Environmental Science, Clark Hall</deliveryPoint><city>Charlottesville</city><administrativeArea>VA</administrativeArea><postalCode>22903</postalCode></address><phone phonetype="voice">(434) 924-0560</phone><phone phonetype="facsimile">(434) 982-2137</phone><electronicMailAddress>lkb2e@virginia.edu</electronicMailAddress></creator><creator scope="document"><individualName><salutation>Ms.</salutation><givenName>Debbie</givenName><surName>Daniel</surName></individualName><address scope="document"><deliveryPoint>Central Environmental lab, biology Department, East Carolina University</deliveryPoint><city>Greenville</city><administrativeArea>NC</administrativeArea><postalCode>27858</postalCode><country>USA</country></address><phone phonetype="voice">252-328-6287</phone><phone phonetype="facsimile">252-328-4178</phone><electronicMailAddress>danield@mail.ecu.edu</electronicMailAddress></creator><creator scope="document"><individualName><salutation>Dr.</salutation><givenName>Robert</givenName><surName>Christian</surName></individualName><address scope="document"><deliveryPoint>East Carolina University, Department of Biology</deliveryPoint><city>Greenville</city><administrativeArea>NC</administrativeArea><postalCode>27858-4353</postalCode></address><phone phonetype="voice">(252) 328-1835</phone><phone phonetype="facsimile">(252) 328-4178</phone><electronicMailAddress>christianr@ecu.edu</electronicMailAddress></creator><metadataProvider scope="document"><organizationName>Virginia Coast Reserve Long-Term Ecological Research Project</organizationName><address scope="document"><deliveryPoint>Department of Environmental Sciences, University of Virginia, 291 McCormick Road, PO Box 400123</deliveryPoint><city>Charlottesville</city><administrativeArea>VA</administrativeArea><postalCode>22904-4123</postalCode><country>USA</country></address><phone phonetype="voice">434-924-7761</phone><phone phonetype="facsimile">434-982-2137</phone><onlineUrl>http://www.vcrlter.virginia.edu</onlineUrl></metadataProvider><pubDate>2000-12-31</pubDate><abstract><section><para>NOTE for Total Suspended Solids, this dataset is superceded by
dataset VCR08144 Total Suspended Solids, Particulate Inorganic and
Organic Matter, and VCR09167 for Chlorophyll and Phaeophytin.</para></section></abstract><keywordSet><keyword keywordType="theme">Inorganic Nutrients</keyword><keyword keywordType="theme">Organic Matter</keyword><keyword keywordType="theme">System State/Condition</keyword><keyword keywordType="theme">total suspended solids</keyword><keyword keywordType="theme">organics</keyword><keyword keywordType="theme">chlorophyll</keyword><keyword keywordType="theme">phaeophytin</keyword></keywordSet><intellectualRights><section><title>Data License</title><para>Data and documentation is copyrighted by The Virginia Coast Reserve LTER
                    project of the University of Virginia (UVA), and ownership remains with the UVA.</para><para>The UVA grants you (hereafter, Licensee) a license to use the data and
                    documentation for academic, and research purposes only, without a fee.</para><para>Licensee may make derivative works. However, if Licensee distributes any
                    derivative work based on or derived from the data and documentation, then
                    Licensee will</para><para><orderedlist><listitem><para>notify the VCR/LTER designated contact (typically the investigator
                                who collected the data) regarding its distribution of the derivative
                                work, and</para></listitem><listitem><para>clearly notify users that such derivative work is a modified
                                version and not the original data and documentation distributed by
                                the UVA.</para></listitem><listitem><para>acknowledge the support of NSF Grants BSR-8702333-06, DEB-9211772,
                                DEB-9411974, DEB-0080381 and DEB-0621014 in any publications using the data and documentation.</para></listitem><listitem><para>send to the address, above, two reprints of any publications
                                resulting from use of the data and documentation.</para></listitem></orderedlist></para><para>Any Licensee wishing to make commercial use of the data and documentation
                    should contact the UVA, c/o VCR/LTER, to negotiate an appropriate license for
                    such commercial use. Commercial use includes</para><para><orderedlist><listitem><para>integration of all or part of the data and documentation into a
                                product for sale or license by or on behalf of Licensee to third
                                parties, or</para></listitem><listitem><para>distribution of the data or documentation to third parties that
                                need it to utilize a commercial product sold or licensed by or on
                                behalf of Licensee.</para></listitem></orderedlist></para><para><emphasis>UVA MAKES NO REPRESENTATIONS ABOUT THE SUITABILITY OF THIS DATA AND
                        DOCUMENTATION FOR ANY PURPOSE. IT IS PROVIDED &quot;AS IS&quot; WITHOUT EXPRESS OR
                        IMPLIED WARRANTY. THE UVA SHALL NOT BE LIABLE FOR ANY DAMAGES SUFFERED BY
                        THE USERS OF THIS DATA AND DOCUMENTATION.</emphasis></para><para>By using or copying this data and documentation, Licensee agrees to abide by
                    the copyright law and all other applicable laws of the U.S. including, but not
                    limited to, export control laws, and the terms of this license. UVA shall have
                    the right to terminate this license immediately by written notice upon
                    Licensee&apos;s breach of, or non-compliance with, any of its terms. Licensee may be
                    held legally responsible for any copyright infringement that is caused or
                    encouraged by Licensee&apos;s failure to abide by the terms of this license.</para></section></intellectualRights><distribution scope="document"><online><url function="download">http://www.vcrlter.virginia.edu/cgi-bin/w3-msql2/data/query/datasets/show_data.html?QDATA_ID=VCR00074</url></online></distribution><coverage scope="document"><geographicCoverage scope="document"><geographicDescription>Phillips Creek, mouth - Phillips Creek, mouth</geographicDescription><boundingCoordinates><westBoundingCoordinate>-75.834712</westBoundingCoordinate><eastBoundingCoordinate>-75.834712</eastBoundingCoordinate><northBoundingCoordinate>37.443925</northBoundingCoordinate><southBoundingCoordinate>37.443925</southBoundingCoordinate></boundingCoordinates></geographicCoverage><geographicCoverage scope="document"><geographicDescription>Phillips Creek Head - Phillips Creek Head</geographicDescription><boundingCoordinates><westBoundingCoordinate>-75.807060</westBoundingCoordinate><eastBoundingCoordinate>-75.807060</eastBoundingCoordinate><northBoundingCoordinate>37.447640</northBoundingCoordinate><southBoundingCoordinate>37.447640</southBoundingCoordinate></boundingCoordinates></geographicCoverage><geographicCoverage scope="document"><geographicDescription>Greens Creek - Greens Creek</geographicDescription><boundingCoordinates><westBoundingCoordinate>-75.807060</westBoundingCoordinate><eastBoundingCoordinate>-75.807060</eastBoundingCoordinate><northBoundingCoordinate>37.484510</northBoundingCoordinate><southBoundingCoordinate>37.484510</southBoundingCoordinate></boundingCoordinates></geographicCoverage><geographicCoverage scope="document"><geographicDescription>Red Banks - Red Banks</geographicDescription><boundingCoordinates><westBoundingCoordinate>-75.805370</westBoundingCoordinate><eastBoundingCoordinate>-75.805370</eastBoundingCoordinate><northBoundingCoordinate>37.461490</northBoundingCoordinate><southBoundingCoordinate>37.461490</southBoundingCoordinate></boundingCoordinates></geographicCoverage><geographicCoverage scope="document"><geographicDescription>Cattleshed Creek mouth - Cattleshed Creek mouth</geographicDescription><boundingCoordinates><westBoundingCoordinate>-75.688870</westBoundingCoordinate><eastBoundingCoordinate>-75.688870</eastBoundingCoordinate><northBoundingCoordinate>37.443382</northBoundingCoordinate><southBoundingCoordinate>37.443382</southBoundingCoordinate></boundingCoordinates></geographicCoverage><geographicCoverage scope="document"><geographicDescription>Cattleshed Creek head - Cattleshed Creek head</geographicDescription><boundingCoordinates><westBoundingCoordinate>-75.685100</westBoundingCoordinate><eastBoundingCoordinate>-75.685100</eastBoundingCoordinate><northBoundingCoordinate>37.442550</northBoundingCoordinate><southBoundingCoordinate>37.442550</southBoundingCoordinate></boundingCoordinates></geographicCoverage><geographicCoverage scope="document"><geographicDescription>No Name Creek - No Name Creek</geographicDescription><boundingCoordinates><westBoundingCoordinate>-75.687560</westBoundingCoordinate><eastBoundingCoordinate>-75.687560</eastBoundingCoordinate><northBoundingCoordinate>37.436930</northBoundingCoordinate><southBoundingCoordinate>37.436930</southBoundingCoordinate></boundingCoordinates></geographicCoverage><geographicCoverage scope="document"><geographicDescription>Quinby Inlet - core - Quinby Inlet - core</geographicDescription><boundingCoordinates><westBoundingCoordinate>-75.692680</westBoundingCoordinate><eastBoundingCoordinate>-75.692680</eastBoundingCoordinate><northBoundingCoordinate>37.452271</northBoundingCoordinate><southBoundingCoordinate>37.452271</southBoundingCoordinate></boundingCoordinates></geographicCoverage><geographicCoverage scope="document"><geographicDescription>Phillips Creek resampled coming back in to shore - Phillips Creek resampled coming back in to shore</geographicDescription><boundingCoordinates><westBoundingCoordinate>-75.835010</westBoundingCoordinate><eastBoundingCoordinate>-75.835010</eastBoundingCoordinate><northBoundingCoordinate>37.445520</northBoundingCoordinate><southBoundingCoordinate>37.445520</southBoundingCoordinate></boundingCoordinates></geographicCoverage><geographicCoverage scope="document"><geographicDescription>Oyster Harbor - Oyster Harbor</geographicDescription><boundingCoordinates><westBoundingCoordinate>-75.924270</westBoundingCoordinate><eastBoundingCoordinate>-75.924270</eastBoundingCoordinate><northBoundingCoordinate>37.289190</northBoundingCoordinate><southBoundingCoordinate>37.289190</southBoundingCoordinate></boundingCoordinates></geographicCoverage><geographicCoverage scope="document"><geographicDescription>Machipongo Inlet - Machipongo Inlet</geographicDescription><boundingCoordinates><westBoundingCoordinate>-75.735920</westBoundingCoordinate><eastBoundingCoordinate>-75.735920</eastBoundingCoordinate><northBoundingCoordinate>37.367640</northBoundingCoordinate><southBoundingCoordinate>37.367640</southBoundingCoordinate></boundingCoordinates></geographicCoverage><geographicCoverage scope="document"><geographicDescription>South Hog - South Hog</geographicDescription><boundingCoordinates><westBoundingCoordinate>-75.718110</westBoundingCoordinate><eastBoundingCoordinate>-75.718110</eastBoundingCoordinate><northBoundingCoordinate>37.381990</northBoundingCoordinate><southBoundingCoordinate>37.381990</southBoundingCoordinate></boundingCoordinates></geographicCoverage><temporalCoverage scope="document"><rangeOfDates><beginDate><calendarDate>1992-07-01</calendarDate></beginDate><endDate><calendarDate>2004-10-26</calendarDate></endDate></rangeOfDates></temporalCoverage></coverage><maintenance><description><para>Data are updated as needed</para></description><maintenanceUpdateFrequency>asNeeded</maintenanceUpdateFrequency></maintenance><contact scope="document"><individualName><salutation>Dr.</salutation><givenName>Robert</givenName><surName>Christian</surName></individualName><address scope="document"><deliveryPoint>East Carolina University, Department of Biology</deliveryPoint><city>Greenville</city><administrativeArea>NC</administrativeArea><postalCode>27858-4353</postalCode></address><phone phonetype="voice">(252) 328-1835</phone><phone phonetype="facsimile">(252) 328-4178</phone><electronicMailAddress>christianr@ecu.edu</electronicMailAddress></contact><contact scope="document"><individualName><salutation>Dr.</salutation><givenName>Robert</givenName><surName>Christian</surName></individualName><address scope="document"><deliveryPoint>East Carolina University, Department of Biology</deliveryPoint><city>Greenville</city><administrativeArea>NC</administrativeArea><postalCode>27858-4353</postalCode></address><phone phonetype="voice">(252) 328-1835</phone><phone phonetype="facsimile">(252) 328-4178</phone><electronicMailAddress>christianr@ecu.edu</electronicMailAddress></contact><contact scope="document"><individualName><salutation>Dr.</salutation><givenName>Robert</givenName><surName>Christian</surName></individualName><address scope="document"><deliveryPoint>East Carolina University, Department of Biology</deliveryPoint><city>Greenville</city><administrativeArea>NC</administrativeArea><postalCode>27858-4353</postalCode></address><phone phonetype="voice">(252) 328-1835</phone><phone phonetype="facsimile">(252) 328-4178</phone><electronicMailAddress>christianr@ecu.edu</electronicMailAddress></contact><contact scope="document"><individualName><salutation>Dr.</salutation><givenName>Robert</givenName><surName>Christian</surName></individualName><address scope="document"><deliveryPoint>East Carolina University, Department of Biology</deliveryPoint><city>Greenville</city><administrativeArea>NC</administrativeArea><postalCode>27858-4353</postalCode></address><phone phonetype="voice">(252) 328-1835</phone><phone phonetype="facsimile">(252) 328-4178</phone><electronicMailAddress>christianr@ecu.edu</electronicMailAddress></contact><contact id="im" scope="document"><positionName>Information manager - Virginia Coast Reserve Long-Term Ecological Research Project</positionName><address scope="document"><deliveryPoint>Department of Environmental Sciences, University of Virginia, 291 McCormick Road, PO Box 400123</deliveryPoint><city>Charlottesville</city><administrativeArea>VA</administrativeArea><postalCode>22904-4123</postalCode><country>USA</country></address><phone phonetype="voice">434-924-8999</phone><phone phonetype="facsimile">434-982-2137</phone><electronicMailAddress>jporter@lternet.edu</electronicMailAddress><onlineUrl>http://www.vcrlter.virginia.edu/jhp7e.html</onlineUrl></contact><publisher scope="document"><organizationName>Virginia Coast Reserve Long-Term Ecological Research Project</organizationName><address scope="document"><deliveryPoint>Department of Environmental Sciences, University of Virginia, 291 McCormick Road, PO Box 400123</deliveryPoint><city>Charlottesville</city><administrativeArea>VA</administrativeArea><postalCode>22904-4123</postalCode><country>USA</country></address><phone phonetype="voice">434-924-7761</phone><phone phonetype="facsimile">434-982-2137</phone><onlineUrl>http://www.vcrlter.virginia.edu</onlineUrl></publisher><pubPlace>Charlottesville, Virginia</pubPlace><methods><methodStep><description><section><para><emphasis>This section contains methods for the general
project.</emphasis></para><para>Nutrient and chlorophyll analyses are were conducted at the Central
Environmental Facility at East Carolina University under the
direction of Debbie Daniel until early 2005. From 2005 until
present day, nutrient analyses are conducted at the University of
Virginia. Analysis are currently run by Meg Miller at the
University of Virginia, you may contact her at
mtm3hq@cms.mail.virginia.edu for information concerning methods.
Chlorophyll-a analysis will be conducted at the UVA Anheuser Busch
Coastal Reasearch Center starting in late 2008.</para><para>Sites (sampled within 2 hours of either side of low tide,
preferably on the falling tide ):</para><para>Machipongo Transect:</para><para><orderedlist><listitem><para>PCM: Mouth of Phillips Creek Creek.</para></listitem><listitem><para>PCH: Head of Phillips Creek (or at least where boat can reach).
(retired site)</para></listitem><listitem><para>GC: Greens Creek near the mouth. (retired site)</para></listitem><listitem><para>RB: Red Bank Creek at confluence with Machipongo River.</para></listitem><listitem><para>CSM: Mouth of Cattleshed Creek.</para></listitem><listitem><para>CSH: Head of Cattleshed Creek (or at least where boat can
reach). (retired site)</para></listitem><listitem><para>NC: Mouth of Noname Creek just south of Cattleshed on Hog
Island. . was initially designated &quot;?&quot;.) (retired site)</para></listitem><listitem><para>QI: Quinby Inlet.</para></listitem><listitem><para>PCB: Mouth of Phillips Creek on return. (Higher tide). (retired
site)</para></listitem><listitem><para>CRm: Creek Site (formerly OH: Oyster Harbor)</para></listitem><listitem><para>MI: Machipongo Inlet</para></listitem><listitem><para>SH: South Hog.</para></listitem><listitem><para>SS: Shoal Site</para></listitem></orderedlist></para><para>Oyster Transect:</para><para><orderedlist><listitem><para>SSI: Sand Shoal Inlet</para></listitem><listitem><para>LC: Little Cobb</para></listitem><listitem><para>NM: New Marsh</para></listitem><listitem><para>RCC: Ramshorn Channel Creek (mouth)</para></listitem><listitem><para>OH: Oyster Harbor</para></listitem><listitem><para>CM: Cobb Mill Creek</para></listitem></orderedlist></para><para>Field sampling (assuming a vertically homogeneous water column,
only surface samples are taken):</para><para><orderedlist><listitem><para>At station the following measures are made: time; temperature,
salinity and conductivity with a YSI SCT meter; air temperature,
dissolved oxygen concentrations and water temperature with a YSI
dissolved oxygen meter; Secchi depth; water depth; wind speed and
direction; and PAR intensity at selected depths.</para></listitem><listitem><para>Three separate samples of water are collected from each
site.</para></listitem></orderedlist></para><para>Oyster Field Laboratory Activities:</para><para><orderedlist><listitem><para>Filtration of water through 0.45 um pore size membrane filters
for nutrient analyses. Approximately 40 ml of filtrate is placed
into individual clean and capped centrifuge tubes. Three samples
are filtered per station, and the tubes are placed in freezer until
being taken to ECU for analysis. (In the first years of the study
ammonium and phosphate analyses were done in Oyster by methods
comparable to those at ECU. Filterable reactive phosphorus samples
were analyzed at both laboratories, and subsequent to 1996 ammonium
analyses were conducted solely at ECU.</para></listitem><listitem><para>Filtration of 300 to 500 ml water through glass fiber filters
(934AH or GFC) is used for chorophyll a analyses. Samples on
filters are frozen until analysis. Prior to 1996, chorophyll a and
phaeopigment concentrations were analyzed on site using 90% acetone
extraction and spectrophotometry (Lorenzen, C.J. 1967. Limnol.
Oceanogr. 12:343). Subsequently, frozen filters are taken to ECU
for analysis.</para></listitem><listitem><para>Filtration of 300 to 500 ml of water through precombusted and
weighed glass fiber filters (934AH or GFC) is done for total
suspended solids and related determinations. Filters with samples
are dried in the oven at 110C for at least 48 h, weighed. The
difference between this mass and that of the filter is the total
suspended solid mass which is corrected for volume filtered to
determine concentration. The filters plus samples are then
combusted for ash free dry mass. This is used to compute both
organic and inorganic matter concentrations.</para></listitem></orderedlist></para><para>UPDATED OYSTER FIELD AND LABORATORY ACTIVITIES :</para><para><orderedlist><listitem><para>Nutrient Analysis: 300mL of water are filtered through a 0.45um
GFC membrane filters. Approximately 250mL of the filtrate is placed
into a large, sterile whirlpak bag for nitrate and phosphate
analysis, the remaining 25-50mL is placed into a smaller whirlpak
bag for DON analysis. Three replicates are done per site. Samples
are frozen after filtration until analysis.</para></listitem><listitem><para>Cholorophyll-a Analysis: 300mL of water are filtered through a
0.45um GFC membrane filter. Filters are folded and placed into
labeled foil envelopes, then frozen until analysis. Three
replicates are done per site.</para></listitem><listitem><para>TSS Analysis: 0.45um GFC membrane filters are placed into
pre-labeled foil envelopes then combusted for 4-6 hours at 450C.
Filter and envelope packets are then weighed for “tare
weight”. 300mL’s of water are filtered through these
precombusted filters. Filters are then placed back into their
envelopes and dried at 60C for several days until samples are
completely dry. Filter packets are then weighed for “dry
weight”. The difference between the “tare weight”
and the “dry weight” is the total suspended solid mass,
which is corrected for volume filtered to determine concentration.
The filter packets are then combusted at 450C for 4-6 hours, then
weighed again to determine Ash Free Dry Mass. This is used to
compute both organic and inorganic matter concentrations.</para></listitem></orderedlist></para><para>1997 to 2005: Activities at East Carolina University:</para><para><orderedlist><listitem><para>Nitrate plus nitrite and filterable reactive phosphorus are
analyzed using an Orion Scientific Instruments Corporation
segmented flow analyzer ( USEPA 1979. Methods for chemical analysis
of water and wastes.)</para></listitem><listitem><para>Ammonium analyses are done manually using the phenohypochlorite
method (Solorzano, L. 1969. Limnol. Oceanogr. 25:403) modified for
small sample size.</para></listitem><listitem><para>Data are managed by individual sampling date usng spreadsheets,
and summary data organized for submission to web pages.</para></listitem></orderedlist></para><para>2005 to Current: Activities at the University of Virginia:</para><para><orderedlist><listitem><para>Nutrients are analyzed using a QuikChem 8500 Automated Ion
analyzer. Analysis is currently conducted by Meg Miller
(mtm3hq@cms.mail.virginia.edu).</para></listitem><listitem><para>Data are managed by individual sampling date using
spreadsheets, and summary data is organized for submission to web
pages.</para></listitem></orderedlist></para><para><emphasis>This section contains a progress report on the general
project.</emphasis></para><para>The project is ongoing. Near monthly sampling has been in force
since summer 1992. As a result of boat and weather problems, winter
and spring 1996 were undersampled.</para><para>Starting in July of 2008, sampling went to Quarterly and was
combined with Quarterly algal sampling.</para></section></description></methodStep></methods><project scope="document"><title>Water quality monitoring of tidal creeks and lagoon</title><personnel scope="document"><individualName><salutation>Dr.</salutation><givenName>Robert</givenName><surName>Christian</surName></individualName><address scope="document"><deliveryPoint>East Carolina University, Department of Biology</deliveryPoint><city>Greenville</city><administrativeArea>NC</administrativeArea><postalCode>27858-4353</postalCode></address><phone phonetype="voice">(252) 328-1835</phone><phone phonetype="facsimile">(252) 328-4178</phone><electronicMailAddress>christianr@ecu.edu</electronicMailAddress><role>originator</role></personnel><abstract><section><para>This is a monitoring program to provide a long-term record of
nutrient concentrations and other water quality variables from the
VCR lagoonal and tidal creek waters. This information provides
background for studies in the aquatic and wetland environments.</para><para>Further this study was designed to follow up on the water
quality monitoring by Lagara earlier.</para></section></abstract></project><access authSystem="knb" scope="document" order="allowFirst"><allow><principal>public</principal><permission>read</permission></allow><allow><principal>uid=VCR,o=lter,dc=ecoinformatics,dc=org</principal><permission>all</permission></allow></access><dataTable scope="document"><entityName>VCR00074</entityName><entityDescription>Water Quality of Virginia Coastal Bays - Total suspended solids and chlorophyll data 1992-2004</entityDescription><physical scope="document"><objectName>VCR00074</objectName><characterEncoding>ASCII</characterEncoding><dataFormat><textFormat><attributeOrientation>column</attributeOrientation><simpleDelimited><fieldDelimiter>,</fieldDelimiter><quoteCharacter>&quot;</quoteCharacter><literalCharacter>\</literalCharacter></simpleDelimited></textFormat></dataFormat></physical><attributeList><attribute id="VCR00074.SITE" scope="document"><attributeName>SITE</attributeName><attributeLabel>SAMPLE SITE OR STATION</attributeLabel><attributeDefinition>SITE - SAMPLE SITE OR STATION</attributeDefinition><storageType typeSystem="http://www.w3.org/2001/XMLSchema-datatypes">string</storageType><measurementScale><nominal><nonNumericDomain><enumeratedDomain enforced="yes"><codeDefinition><code>CM</code><definition>Cobb Mill Creek (where it crosses under Crumb Hill Road)</definition></codeDefinition><codeDefinition><code>CSH</code><definition>Cattleshed Headwaters</definition></codeDefinition><codeDefinition><code>CSM</code><definition>Cattle Shed Mouth</definition></codeDefinition><codeDefinition><code>GC</code><definition>Green Creek</definition></codeDefinition><codeDefinition><code>LC</code><definition>Little Cobb</definition></codeDefinition><codeDefinition><code>MI</code><definition>Machipongo Inlet</definition></codeDefinition><codeDefinition><code>NC</code><definition>Noname Creek</definition></codeDefinition><codeDefinition><code>NM</code><definition>New Marsh</definition></codeDefinition><codeDefinition><code>OH</code><definition>Oyster Harbor</definition></codeDefinition><codeDefinition><code>PCB</code><definition>Phillips Creek Back</definition></codeDefinition><codeDefinition><code>PCH</code><definition>Phillips Creek Headwaters</definition></codeDefinition><codeDefinition><code>PCM</code><definition>Phillips Creek Mouth</definition></codeDefinition><codeDefinition><code>QI</code><definition>Quinby Inlet</definition></codeDefinition><codeDefinition><code>RB</code><definition>Redbank Creek</definition></codeDefinition><codeDefinition><code>RCC</code><definition>Ramshorn Channel Creek</definition></codeDefinition><codeDefinition><code>SH</code><definition>South Hog</definition></codeDefinition><codeDefinition><code>SSI</code><definition>Sand Shoal Inlet</definition></codeDefinition></enumeratedDomain></nonNumericDomain></nominal></measurementScale></attribute><attribute id="VCR00074.DATE" scope="document"><attributeName>DATE</attributeName><attributeLabel>DATE SAMPLE COLLECTED</attributeLabel><attributeDefinition>DATE - DATE SAMPLE COLLECTED</attributeDefinition><storageType typeSystem="http://www.w3.org/2001/XMLSchema-datatypes">string</storageType><measurementScale><nominal><nonNumericDomain><textDomain><definition>DATE SAMPLE COLLECTED</definition></textDomain></nonNumericDomain></nominal></measurementScale></attribute><attribute id="VCR00074.OVEN" scope="document"><attributeName>OVEN</attributeName><attributeLabel>OVEN DRY WEIGHT</attributeLabel><attributeDefinition>OVEN - OVEN DRY WEIGHT</attributeDefinition><storageType typeSystem="http://www.w3.org/2001/XMLSchema-datatypes">float</storageType><measurementScale><interval><unit><customUnit>mg/L</customUnit></unit><numericDomain><numberType>real</numberType><bounds><minimum exclusive="false">0.000</minimum></bounds></numericDomain></interval></measurementScale><missingValueCode><code>NS</code><codeExplanation>missing</codeExplanation></missingValueCode><missingValueCode><code>NV</code><codeExplanation>missing</codeExplanation></missingValueCode><missingValueCode><code>NR</code><codeExplanation>missing</codeExplanation></missingValueCode></attribute><attribute id="VCR00074.ASH" scope="document"><attributeName>ASH</attributeName><attributeLabel>ASH WEIGHT</attributeLabel><attributeDefinition>ASH - ASH WEIGHT</attributeDefinition><storageType typeSystem="http://www.w3.org/2001/XMLSchema-datatypes">float</storageType><measurementScale><interval><unit><customUnit>mg/L</customUnit></unit><numericDomain><numberType>real</numberType><bounds><minimum exclusive="false">0.000</minimum></bounds></numericDomain></interval></measurementScale><missingValueCode><code>NS</code><codeExplanation>missing</codeExplanation></missingValueCode><missingValueCode><code>NV</code><codeExplanation>missing</codeExplanation></missingValueCode><missingValueCode><code>NR</code><codeExplanation>missing</codeExplanation></missingValueCode></attribute><attribute id="VCR00074.ORG" scope="document"><attributeName>ORG</attributeName><attributeLabel>ORGANIC WEIGHT</attributeLabel><attributeDefinition>ORG - ORGANIC WEIGHT</attributeDefinition><storageType typeSystem="http://www.w3.org/2001/XMLSchema-datatypes">float</storageType><measurementScale><interval><unit><customUnit>mg/L</customUnit></unit><numericDomain><numberType>real</numberType><bounds><minimum exclusive="false">0.000</minimum></bounds></numericDomain></interval></measurementScale><missingValueCode><code>NS</code><codeExplanation>missing</codeExplanation></missingValueCode><missingValueCode><code>NV</code><codeExplanation>missing</codeExplanation></missingValueCode><missingValueCode><code>NR</code><codeExplanation>missing</codeExplanation></missingValueCode></attribute><attribute id="VCR00074.LTERCHLA" scope="document"><attributeName>LTERCHLA</attributeName><attributeLabel>CHLOROPHYLL A</attributeLabel><attributeDefinition>LTERCHLA - CHLOROPHYLL A</attributeDefinition><storageType typeSystem="http://www.w3.org/2001/XMLSchema-datatypes">float</storageType><measurementScale><interval><unit><customUnit>ug/L</customUnit></unit><numericDomain><numberType>real</numberType><bounds><minimum exclusive="false">0.000</minimum></bounds></numericDomain></interval></measurementScale><missingValueCode><code>NS</code><codeExplanation>missing</codeExplanation></missingValueCode><missingValueCode><code>NV</code><codeExplanation>missing</codeExplanation></missingValueCode><missingValueCode><code>NR</code><codeExplanation>missing</codeExplanation></missingValueCode></attribute><attribute id="VCR00074.LTERPHA" scope="document"><attributeName>LTERPHA</attributeName><attributeLabel>PHAEOPHYTIN</attributeLabel><attributeDefinition>LTERPHA - PHAEOPHYTIN</attributeDefinition><storageType typeSystem="http://www.w3.org/2001/XMLSchema-datatypes">float</storageType><measurementScale><interval><unit><customUnit>ug/L</customUnit></unit><numericDomain><numberType>real</numberType><bounds><minimum exclusive="false">0.000</minimum></bounds></numericDomain></interval></measurementScale><missingValueCode><code>NS</code><codeExplanation>missing</codeExplanation></missingValueCode><missingValueCode><code>NV</code><codeExplanation>missing</codeExplanation></missingValueCode><missingValueCode><code>NR</code><codeExplanation>missing</codeExplanation></missingValueCode></attribute></attributeList></dataTable></dataset><additionalMetadata><stmml:unitList convention="CML"><stmml:unit id="none" multiplierToSI="1.0" constantToSI="0.0"></stmml:unit><stmml:unit id="mg/L" multiplierToSI="1.0" constantToSI="0.0"></stmml:unit><stmml:unit id="ug/L" multiplierToSI="1.0" constantToSI="0.0"></stmml:unit></stmml:unitList></additionalMetadata></eml:eml>