<DryadDataFile xmlns="http://purl.org/dryad/schema/terms/v3.1" xmlns:dwc="http://rs.tdwg.org/dwc/terms/" xmlns:dcterms="http://purl.org/dc/terms/" xmlns:bibo="http://purl.org/dryad/schema/dryad-bibo/v3.1" xmlns:xsi="http://www.w3.org/2001/XMLSchema-instance" xsi:schemaLocation="http://purl.org/dryad/schema/terms/v3.1 http://datadryad.org/profile/v3.1/dryad.xsd">
  <dcterms:type>file</dcterms:type>
  <dcterms:creator>Sofaer, Helen R.</dcterms:creator>
  <dcterms:creator>Sillett, T. Scott</dcterms:creator>
  <dcterms:creator>Langin, Kathryn M.</dcterms:creator>
  <dcterms:creator>Morrison, Scott A.</dcterms:creator>
  <dcterms:creator>Ghalambor, Cameron K.</dcterms:creator>
  <dcterms:title>Sofaer_etal_OCWANestSurvival</dcterms:title>
  <dcterms:identifier>https://doi.org/10.5061/dryad.m4fs7/2</dcterms:identifier>
  <dcterms:rights>http://creativecommons.org/publicdomain/zero/1.0/</dcterms:rights>
  <dcterms:description>Orange-crowned warbler nest survival data.</dcterms:description>
  <dcterms:subject>Demography</dcterms:subject>
  <dcterms:subject>density dependence</dcterms:subject>
  <dcterms:subject>fecundity</dcterms:subject>
  <dcterms:subject>island syndrome</dcterms:subject>
  <dcterms:subject>nest predation</dcterms:subject>
  <dcterms:subject>zero- inflated model</dcterms:subject>
  <dwc:scientificName>Oreothlypis celata</dwc:scientificName>
  <dcterms:spatial>Santa Catalina Island California</dcterms:spatial>
  <dcterms:dateSubmitted>2014-06-06T18:47:21Z</dcterms:dateSubmitted>
  <dcterms:available>2014-06-06T18:47:21Z</dcterms:available>
  <dcterms:provenance>Step: dryadAcceptEditReject - action:dryadAcceptEditRejectAction Entered publication blackout by Rachel Walton(rwalton@live.unc.edu) on 2014-05-27T20:04:08Z (GMT)</dcterms:provenance>
  <dcterms:provenance>Made available in DSpace on 2014-06-06T18:47:21Z (GMT). No. of bitstreams: 1
Sofaer_etal_OCWANestSurvival.csv: 15220 bytes, checksum: 9cd030bbeb5f0a898a877e04ec0b76ca (MD5)</dcterms:provenance>
  <dcterms:isPartOf>https://doi.org/10.5061/dryad.m4fs7</dcterms:isPartOf>
</DryadDataFile>